secretelf/__init__.py
secretelf/_version.py
secretelf/_version.py~
secretelf/cli.py
secretelf/cli.py~
secretelf/iaskeys.py
secretelf/iaskeys.py~
secretelf-0.1.1.dist-info/METADATA
secretelf-0.1.1.dist-info/WHEEL
secretelf-0.1.1.dist-info/entry_points.txt
secretelf-0.1.1.dist-info/licenses/LICENSE.txt
secretelf-0.1.1.dist-info/RECORD
