Metadata-Version: 2.1
Name: secretelf
Version: 0.1.1
Project-URL: Documentation, https://github.com/sbellem/secretelf#readme
Project-URL: Issues, https://github.com/sbellem/secretelf/issues
Project-URL: Source, https://github.com/sbellem/secretelf
Author-email: Sylvain Bellemare <sbellem@gmail.com>
License-Expression: MIT
License-File: LICENSE.txt
Classifier: Development Status :: 2 - Pre-Alpha
Classifier: Programming Language :: Python
Classifier: Programming Language :: Python :: 3.7
Classifier: Programming Language :: Python :: 3.8
Classifier: Programming Language :: Python :: 3.9
Classifier: Programming Language :: Python :: 3.10
Classifier: Programming Language :: Python :: 3.11
Classifier: Programming Language :: Python :: Implementation :: CPython
Requires-Python: >=3.7
Requires-Dist: click
Requires-Dist: pyelftools
